curb/Config.py
curb/Wrappers.py
curb/__init__.py
curb/__main__.py
curb-0.0.4.dist-info/METADATA
curb-0.0.4.dist-info/WHEEL
curb-0.0.4.dist-info/top_level.txt
curb-0.0.4.dist-info/RECORD
