Metadata-Version: 2.1
Name: curb
Version: 0.0.4
Summary: A minimalist module to containerize child processes
Home-page: https://github.com/raghavmecheri/curb
Author: Raghav Mecheri
Author-email: raghav@binit.in
License: MIT
Download-URL: https://github.com/raghavmecheri/curb/archive/curb-0.0.4
Platform: UNKNOWN
Classifier: Development Status :: 3 - Alpha
Classifier: Intended Audience :: Science/Research
Classifier: License :: OSI Approved :: MIT License
Classifier: Operating System :: POSIX :: Linux
Classifier: Operating System :: MacOS :: MacOS X
Classifier: Operating System :: Microsoft :: Windows :: Windows 10
Classifier: Programming Language :: Python :: 3.8
Requires-Dist: click (==8.0.1)
Requires-Dist: psutil (==5.8.0)
